{
  "version": 1,
  "id": "water2",
  "file": "ww.png",
  "displayScale": 0.666667,
  "frameMs": 180,
  "frameWidth": 48,
  "frameHeight": 48,
  "frames": {
    "loop_0": {
      "x": 0,
      "y": 0,
      "w": 48,
      "h": 48
    },
    "loop_1": {
      "x": 48,
      "y": 0,
      "w": 48,
      "h": 48
    },
    "loop_2": {
      "x": 96,
      "y": 0,
      "w": 48,
      "h": 48
    },
    "loop_3": {
      "x": 0,
      "y": 48,
      "w": 48,
      "h": 48
    },
    "loop_4": {
      "x": 48,
      "y": 48,
      "w": 48,
      "h": 48
    },
    "loop_5": {
      "x": 96,
      "y": 48,
      "w": 48,
      "h": 48
    },
    "loop_6": {
      "x": 0,
      "y": 96,
      "w": 48,
      "h": 48
    },
    "loop_7": {
      "x": 48,
      "y": 96,
      "w": 48,
      "h": 48
    },
    "loop_8": {
      "x": 96,
      "y": 96,
      "w": 48,
      "h": 48
    }
  },
  "gearUseTarget": true
}
